LICENCE.txt
MANIFEST.in
README.rst
setup.py
PO_Projects.egg-info/PKG-INFO
PO_Projects.egg-info/SOURCES.txt
PO_Projects.egg-info/dependency_links.txt
PO_Projects.egg-info/not-zip-safe
PO_Projects.egg-info/requires.txt
PO_Projects.egg-info/top_level.txt
po_projects/__init__.py
po_projects/admin.py
po_projects/assets.py
po_projects/crumbs.py
po_projects/dump.py
po_projects/generators.py
po_projects/mixins.py
po_projects/models.py
po_projects/settings.py
po_projects/urls.py
po_projects/forms/__init__.py
po_projects/forms/catalog.py
po_projects/forms/crispies.py
po_projects/forms/project.py
po_projects/forms/translation.py
po_projects/management/__init__.py
po_projects/management/commands/__init__.py
po_projects/management/commands/popo.py
po_projects/migrations/0001_initial.py
po_projects/migrations/0002_auto__add_field_project_description.py
po_projects/migrations/0003_auto__add_field_project_domain.py
po_projects/migrations/0004_auto__add_field_templatemsg_pluralizable__add_field_templatemsg_python.py
po_projects/migrations/0005_fill_template_python_format_and_pluralizable.py
po_projects/migrations/0006_auto__del_field_templatemsg_flags__add_field_templatemsg_plural_messag.py
po_projects/migrations/0007_auto__add_field_translationmsg_plural_message.py
po_projects/migrations/__init__.py
po_projects/rest/__init__.py
po_projects/rest/serializers.py
po_projects/rest/views.py
po_projects/static/css/po-projects_app.css
po_projects/static/fonts/po-projects.eot
po_projects/static/fonts/po-projects.svg
po_projects/static/fonts/po-projects.ttf
po_projects/static/fonts/po-projects.woff
po_projects/static/js/po-projects/plugins.js
po_projects/templates/po_projects/base.html
po_projects/templates/po_projects/catalog_details.html
po_projects/templates/po_projects/catalog_messages_form.html
po_projects/templates/po_projects/hidden_field.html
po_projects/templates/po_projects/include_css.html
po_projects/templates/po_projects/include_js.html
po_projects/templates/po_projects/input_as_text.html
po_projects/templates/po_projects/project_details.html
po_projects/templates/po_projects/project_form.html
po_projects/templates/po_projects/project_index.html
po_projects/utils/__init__.py
