Metadata-Version: 1.1
Name: PO-Projects
Version: 0.8.1
Summary: Django application to manage PO files for project translations
Home-page: http://pypi.python.org/pypi/PO-Projects
Author: David Thenon
Author-email: dthenon@emencia.com
License: MIT
Platform: UNKNOWN
Classifier: Programming Language :: Python
Classifier: License :: OSI Approved :: MIT License
Classifier: Operating System :: OS Independent
Classifier: Development Status :: 4 - Beta
Classifier: Environment :: Web Environment
Classifier: Framework :: Django
Classifier: Intended Audience :: Developers
Classifier: Topic :: Internet :: WWW/HTTP
Classifier: Topic :: Software Development :: Libraries :: Python Modules
